Metadata-Version: 1.0
Name: reblok
Version: 0.1.3
Summary: Python decompiler
Home-page: http://devedge.bour.cc/wiki/Reblok
Author: Guillaume Bour
Author-email: guillaume@bour.cc
License: GNU General Public License v3
Download-URL: http://devedge.bour.cc/resources/reblok/src/reblok.latest.tar.gz
Platform: UNKNOWN
Classifier: Development Status :: 4 - Beta
Classifier: Environment :: Console
Classifier: Intended Audience :: Developers
Classifier: License :: OSI Approved :: GNU Affero General Public License v3
Classifier: License :: OSI Approved :: GNU General Public License (GPL)
Classifier: Natural Language :: English
Classifier: Natural Language :: French
Classifier: Operating System :: OS Independent
Classifier: Programming Language :: Python
Classifier: Programming Language :: Python :: 2.5
Classifier: Programming Language :: Python :: 2.6
Classifier: Programming Language :: Python :: 2.7
Classifier: Topic :: Software Development
Classifier: Topic :: Software Development :: Disassemblers
Classifier: Topic :: Software Development :: Libraries :: Python Modules
Classifier: Topic :: Utilities
